inspari/config/__init__.py
inspari/config/appsettings.py
inspari/config/keyvault.py
inspari_config-0.1.5.dist-info/METADATA
inspari_config-0.1.5.dist-info/WHEEL
inspari_config-0.1.5.dist-info/RECORD
